skynix_cli/__init__.py
skynix_cli/skynixcli.py
skynix_cli-0.1.3.post4.dist-info/entry_points.txt
skynix_cli-0.1.3.post4.dist-info/LICENSE
skynix_cli-0.1.3.post4.dist-info/WHEEL
skynix_cli-0.1.3.post4.dist-info/METADATA
skynix_cli-0.1.3.post4.dist-info/RECORD
