Metadata-Version: 2.1
Name: skynix-cli
Version: 0.1.3.post4
Summary: 
Author: AbdelrhmanNile
Author-email: abdelrhmannile@gmail.com
Requires-Python: >=3.10,<4.0
Classifier: Programming Language :: Python :: 3
Classifier: Programming Language :: Python :: 3.10
Requires-Dist: typer (>=0.6.1,<0.7.0)
